Workbook

Sheet READ ME
A1: ThermoGen: opportunity projections (INTERNAL)
A2: CONFIDENTIAL. Contains unpublished intellectual-property planning. Do not upload, email outside the company, or paste into the public websites.
A4: What this is | B4: Your four opportunity documents rewritten as projections: stage budgets, the cost of protecting each IP candidate, and three scenarios. Every number is either an input you can change (blue) or a formula (black).
A5: How to use it | B5: 1) Review the blue inputs on 'Assumptions'. 2) Fill the yellow cells (they are things I could not estimate for you). 3) Read the results on 'Roadmap_Budget' and 'Scenarios'. Change an input and everything recalculates.
A6: Colour code | B6: Blue text = an input you can change. Black text = a formula. Green text = a link to another sheet. Yellow fill = a cell for you to fill in or a key assumption.
A7: What is verified | B7: USPTO provisional filing fees ($65 micro, $130 small, $325 large entity; 37 CFR 1.16, effective 19 January 2025) and the market and burden figures on 'Market_Context' (sources named in each row). Confirm fees again before you file, because fee schedules change.
A8: What is an estimate | B8: The four stage budgets are management planning ranges (the same ones shown publicly on the ThermoGen website), the scenario spend positions, and the attorney-cost ranges (one 2026 pricing guide for biotech provisionals, plus your own $5,000 to $15,000 full-application figure). Get real quotes before relying on them.
A9: What is NOT in here | B9: No organism names, no process parameters, no experimental protocols. Keep those in your dated lab notebook.
A10: Not advice | B10: This workbook is a planning aid. It is not legal, tax or investment advice. Ask a patent attorney and an accountant.
A11: Date prepared | B11: 14 October 2026

Sheet Assumptions
A1: Assumptions (edit the blue cells)
A2: Blue = input you can change. Black = formula. Yellow = please fill in. Sources are in the last column of each table.
A4: Roadmap stage | B4: Start month | C4: End month | D4: Budget low (US$) | E4: Budget high (US$) | F4: Basis
A5: 1. Foundation | B5: 0 | C5: 6 | D5: 25000 | E5: 75000 | F5: Management planning estimate, October 2026 (same ranges as the public Projections page). Refine with advisers and real quotes.
A6: 2. Pilot and proof of concept | B6: 6 | C6: 18 | D6: 100000 | E6: 300000 | F6: Management planning estimate, October 2026 (same ranges as the public Projections page). Refine with advisers and real quotes.
A7: 3. Validation and partnerships | B7: 18 | C7: 30 | D7: 300000 | E7: 1000000 | F7: Management planning estimate, October 2026 (same ranges as the public Projections page). Refine with advisers and real quotes.
A8: 4. Licensing and scale | B8: 30 | C8: 48 | D8: 1000000 | E8: 3000000 | F8: Management planning estimate, October 2026 (same ranges as the public Projections page). Refine with advisers and real quotes.
A10: Scenario | B10: Spend position in range (0 = low end, 1 = high end) | F10: What it means
A11: Conservative | B11: 0.35 | F11: Lean path, mostly grant-funded, fewer parallel workstreams.
A12: Base case | B12: 0.6 | F12: Middle path with a sponsored-research or collaboration agreement.
A13: Upside | B13: 0.85 | F13: Ambitious path: more parallel work, faster validation, a licence or option agreement.
A15: IP cost inputs | B15: Value (US$) | F15: Source / note
A16: Entity status for USPTO fees (1 = micro, 2 = small, 3 = large) | B16: 2 | F16: Your choice. Micro and small entity status has eligibility rules: confirm with counsel before claiming it.
A17: USPTO provisional filing fee: micro entity | B17: 65 | F17: 37 CFR 1.16(d), fee schedule effective 19 January 2025. Confirm current fees before filing.
A18: USPTO provisional filing fee: small entity | B18: 130 | F18: Same source.
A19: USPTO provisional filing fee: large entity | B19: 325 | F19: Same source. (Your guide's ~$350 was close to this large-entity fee, not the small-entity fee.)
A20: USPTO provisional fee used in this model | B20: =CHOOSE(B16,B17,B18,B19) -> 130 | F20: Formula: picks the fee for the entity status above.
A21: Attorney preparation of a provisional, biotech: low | B21: 4000 | F21: One 2026 pricing guide (IP Boutique Law) gives $4,000 to $5,000 for biotech or complex software. Get quotes.
A22: Attorney preparation of a provisional, biotech: high | B22: 5000 | F22: Same source.
A23: Full application with prosecution: low | B23: 5000 | F23: Your Patent Opportunities guide: $5,000 to $15,000.
A24: Full application with prosecution: high | B24: 15000 | F24: Your Patent Opportunities guide. Biotech cases often cost more: get a quote.
A25: Foreign / PCT filing allowance per candidate | B25: 0 | F25: NOT ESTIMATED: depends on which countries matter. Ask counsel for a quote and enter it here.
A26: Number of candidates to file | B26: 4 | F26: Your guide lists four candidates. Candidate 4 may be published instead of patented.
A29: Proof-of-concept lab materials (from your Lab Experiments document) | B29: Low (US$) | C29: High (US$) | F29: Source / note
A30: Type strain from a culture collection | B30: 400 | C30: 600 | F30: Your Lab Experiments document (materials table).
A31: Raw dried seaweed biomass | B31: 15 | C31: 40 | F31: Your Lab Experiments document (materials table).
A32: Metal salts (copper, zinc, iron) | B32: 10 | C32: 30 | F32: Your Lab Experiments document (materials table).
A33: Arsenic compound for the spiking test | B33: 30 | C33: 60 | F33: Your Lab Experiments document (materials table).
A34: Portable arsenic field test kit | B34: 50 | C34: 150 | F34: Your Lab Experiments document (materials table).
A35: Hydrogen sulfide colorimetric strips | B35: 15 | C35: 30 | F35: Your Lab Experiments document (materials table).
A36: pH meter or strips | B36: 5 | C36: 25 | F36: Your Lab Experiments document (materials table).
A37: Aquarium air pump and tubing | B37: 5 | C37: 15 | F37: Your Lab Experiments document (materials table).
A38: Sealed jars or containers | B38: 5 | C38: 15 | F38: Your Lab Experiments document (materials table).
A39: Total listed in your document | B39: =SUM(B30:B38) -> 535 | C39: =SUM(C30:C38) -> 965 | F39: Matches the $535 to $965 in your document.
A40: MISSING: copper and zinc test kits (Experiment 1 measures them, but only an arsenic kit is listed) | B40: 0 | C40: 0 | F40: Not in your document. Get quotes and enter them here.
A41: MISSING: personal protective equipment and hazardous-waste disposal (arsenic compounds are toxic) | B41: 0 | C41: 0 | F41: Not in your document. Get quotes and enter them here.
A42: MISSING: institutional safety or biosafety review, and a suitable lab space (a university or contract lab is safer than a private lab) | B42: 0 | C42: 0 | F42: Not in your document. Get quotes and enter them here.
A43: Total lab budget including gaps | B43: =B39+SUM(B40:B42) -> 535 | C43: =C39+SUM(C40:C42) -> 965

Sheet IP_Pipeline
A1: IP pipeline: what each candidate needs, and what protecting it costs
A2: Rule: do not present or publish detailed methods anywhere (talks, papers, grant applications, the website) until the provisional application for that candidate has been filed.
A4: ID | B4: Candidate (internal short name) | C4: Type | D4: What must be shown | E4: Readiness 0 to 5 | F4: Provisional: low (US$) | G4: Provisional: high (US$) | H4: Full application: low (US$) | I4: Full application: high (US$) | J4: Target provisional filing date | K4: Notes from your guide
A5: C1 | B5: Reducing toxicity of decomposing seaweed with hot-spring microbial consortia | C5: Method of use | D5: Dated lab results showing reduced toxic gas and metal levels against an untreated control | E5: 1 | F5: =Assumptions!$B$20+Assumptions!$B$21 -> 4130 | G5: =Assumptions!$B$20+Assumptions!$B$22 -> 5130 | H5: =Assumptions!$B$23 -> 5000 | I5: =Assumptions!$B$24 -> 15000 | K5: Requires documented lab results to support the claim.
A6: C2 | B6: Recovering metals from seaweed biomass with a microbial leaching process | C6: Process | D6: Every step documented precisely, with measured metal recovery | E6: 1 | F6: =Assumptions!$B$20+Assumptions!$B$21 -> 4130 | G6: =Assumptions!$B$20+Assumptions!$B$22 -> 5130 | H6: =Assumptions!$B$23 -> 5000 | I6: =Assumptions!$B$24 -> 15000 | K6: Document the process step by step before filing.
A7: C3 | B7: Integrated multi-product process from seaweed biomass | C7: Process (sequence) | D7: Clear step-by-step claims for the order of the stages and results for each fraction | E7: 1 | F7: =Assumptions!$B$20+Assumptions!$B$21 -> 4130 | G7: =Assumptions!$B$20+Assumptions!$B$22 -> 5130 | H7: =Assumptions!$B$23 -> 5000 | I7: =Assumptions!$B$24 -> 15000 | K7: A process patent; needs clear step-by-step claims.
A8: C4 | B8: Field testing protocol for judging remediation effectiveness | C8: Protocol | D8: Pilot data showing the combination of tests tracks real outcomes | E8: 1 | F8: =Assumptions!$B$20+Assumptions!$B$21 -> 4130 | G8: =Assumptions!$B$20+Assumptions!$B$22 -> 5130 | H8: =Assumptions!$B$23 -> 5000 | I8: =Assumptions!$B$24 -> 15000 | K8: Consider publishing as a citable protocol if a patent is not pursued.
A9: Total | F9: =SUM(F5:F8) -> 16520 | G9: =SUM(G5:G8) -> 20520 | H9: =SUM(H5:H8) -> 20000 | I9: =SUM(I5:I8) -> 60000
A10: Foreign / PCT allowance | F10: =Assumptions!$B$25*Assumptions!$B$26 -> 0 | K10: Zero until you enter a quote on 'Assumptions'.
A11: Provisional stage total (all candidates) | F11: =F9 -> 16520 | G11: =G9 -> 20520
A13: Readiness scale: 0 = idea only; 1 = written description (what you have today); 2 = dated lab notes started; 3 = pilot data; 4 = data supports the claims; 5 = ready to file.
A14: Check: do provisional filings fit inside the Stage 1 budget? | F14: =IF(G11>Assumptions!E5,"NO: raise Stage 1 or file fewer candidates",IF(G11>Assumptions!D5,"Fits, but uses most of the Stage 1 range","Fits comfortably")) -> Fits comfortably

Sheet Roadmap_Budget
A1: Roadmap budget by quarter, three scenarios (US$)
A2: Each stage's budget is spread evenly across its quarters. Scenario spend = low + (high - low) x the spend position on 'Assumptions'.
A4: Quarter | B4: Start month | C4: End month | D4: Stage no. | E4: Quarters in stage | F4: Conservative | G4: Base case | H4: Upside | I4: Cumulative: Conservative | J4: Cumulative: Base case | K4: Cumulative: Upside
A5: Q1 | B5: 0 | C5: =B5+3 -> 3 | D5: =MATCH(B5,Assumptions!$B$5:$B$8,1) -> 1 | E5: =(INDEX(Assumptions!$C$5:$C$8,D5)-INDEX(Assumptions!$B$5:$B$8,D5))/3 -> 2 | F5: =(INDEX(Assumptions!$D$5:$D$8,$D5)+(INDEX(Assumptions!$E$5:$E$8,$D5)-INDEX(Assumptions!$D$5:$D$8,$D5))*Assumptions!$B$11)/$E5 -> 21250 | G5: =(INDEX(Assumptions!$D$5:$D$8,$D5)+(INDEX(Assumptions!$E$5:$E$8,$D5)-INDEX(Assumptions!$D$5:$D$8,$D5))*Assumptions!$B$12)/$E5 -> 27500 | H5: =(INDEX(Assumptions!$D$5:$D$8,$D5)+(INDEX(Assumptions!$E$5:$E$8,$D5)-INDEX(Assumptions!$D$5:$D$8,$D5))*Assumptions!$B$13)/$E5 -> 33750 | I5: =SUM(F$5:F5) -> 21250 | J5: =SUM(G$5:G5) -> 27500 | K5: =SUM(H$5:H5) -> 33750
A6: Q2 | B6: 3 | C6: =B6+3 -> 6 | D6: =MATCH(B6,Assumptions!$B$5:$B$8,1) -> 1 | E6: =(INDEX(Assumptions!$C$5:$C$8,D6)-INDEX(Assumptions!$B$5:$B$8,D6))/3 -> 2 | F6: =(INDEX(Assumptions!$D$5:$D$8,$D6)+(INDEX(Assumptions!$E$5:$E$8,$D6)-INDEX(Assumptions!$D$5:$D$8,$D6))*Assumptions!$B$11)/$E6 -> 21250 | G6: =(INDEX(Assumptions!$D$5:$D$8,$D6)+(INDEX(Assumptions!$E$5:$E$8,$D6)-INDEX(Assumptions!$D$5:$D$8,$D6))*Assumptions!$B$12)/$E6 -> 27500 | H6: =(INDEX(Assumptions!$D$5:$D$8,$D6)+(INDEX(Assumptions!$E$5:$E$8,$D6)-INDEX(Assumptions!$D$5:$D$8,$D6))*Assumptions!$B$13)/$E6 -> 33750 | I6: =SUM(F$5:F6) -> 42500 | J6: =SUM(G$5:G6) -> 55000 | K6: =SUM(H$5:H6) -> 67500
A7: Q3 | B7: 6 | C7: =B7+3 -> 9 | D7: =MATCH(B7,Assumptions!$B$5:$B$8,1) -> 2 | E7: =(INDEX(Assumptions!$C$5:$C$8,D7)-INDEX(Assumptions!$B$5:$B$8,D7))/3 -> 4 | F7: =(INDEX(Assumptions!$D$5:$D$8,$D7)+(INDEX(Assumptions!$E$5:$E$8,$D7)-INDEX(Assumptions!$D$5:$D$8,$D7))*Assumptions!$B$11)/$E7 -> 42500 | G7: =(INDEX(Assumptions!$D$5:$D$8,$D7)+(INDEX(Assumptions!$E$5:$E$8,$D7)-INDEX(Assumptions!$D$5:$D$8,$D7))*Assumptions!$B$12)/$E7 -> 55000 | H7: =(INDEX(Assumptions!$D$5:$D$8,$D7)+(INDEX(Assumptions!$E$5:$E$8,$D7)-INDEX(Assumptions!$D$5:$D$8,$D7))*Assumptions!$B$13)/$E7 -> 67500 | I7: =SUM(F$5:F7) -> 85000 | J7: =SUM(G$5:G7) -> 110000 | K7: =SUM(H$5:H7) -> 135000
A8: Q4 | B8: 9 | C8: =B8+3 -> 12 | D8: =MATCH(B8,Assumptions!$B$5:$B$8,1) -> 2 | E8: =(INDEX(Assumptions!$C$5:$C$8,D8)-INDEX(Assumptions!$B$5:$B$8,D8))/3 -> 4 | F8: =(INDEX(Assumptions!$D$5:$D$8,$D8)+(INDEX(Assumptions!$E$5:$E$8,$D8)-INDEX(Assumptions!$D$5:$D$8,$D8))*Assumptions!$B$11)/$E8 -> 42500 | G8: =(INDEX(Assumptions!$D$5:$D$8,$D8)+(INDEX(Assumptions!$E$5:$E$8,$D8)-INDEX(Assumptions!$D$5:$D$8,$D8))*Assumptions!$B$12)/$E8 -> 55000 | H8: =(INDEX(Assumptions!$D$5:$D$8,$D8)+(INDEX(Assumptions!$E$5:$E$8,$D8)-INDEX(Assumptions!$D$5:$D$8,$D8))*Assumptions!$B$13)/$E8 -> 67500 | I8: =SUM(F$5:F8) -> 127500 | J8: =SUM(G$5:G8) -> 165000 | K8: =SUM(H$5:H8) -> 202500
A9: Q5 | B9: 12 | C9: =B9+3 -> 15 | D9: =MATCH(B9,Assumptions!$B$5:$B$8,1) -> 2 | E9: =(INDEX(Assumptions!$C$5:$C$8,D9)-INDEX(Assumptions!$B$5:$B$8,D9))/3 -> 4 | F9: =(INDEX(Assumptions!$D$5:$D$8,$D9)+(INDEX(Assumptions!$E$5:$E$8,$D9)-INDEX(Assumptions!$D$5:$D$8,$D9))*Assumptions!$B$11)/$E9 -> 42500 | G9: =(INDEX(Assumptions!$D$5:$D$8,$D9)+(INDEX(Assumptions!$E$5:$E$8,$D9)-INDEX(Assumptions!$D$5:$D$8,$D9))*Assumptions!$B$12)/$E9 -> 55000 | H9: =(INDEX(Assumptions!$D$5:$D$8,$D9)+(INDEX(Assumptions!$E$5:$E$8,$D9)-INDEX(Assumptions!$D$5:$D$8,$D9))*Assumptions!$B$13)/$E9 -> 67500 | I9: =SUM(F$5:F9) -> 170000 | J9: =SUM(G$5:G9) -> 220000 | K9: =SUM(H$5:H9) -> 270000
A10: Q6 | B10: 15 | C10: =B10+3 -> 18 | D10: =MATCH(B10,Assumptions!$B$5:$B$8,1) -> 2 | E10: =(INDEX(Assumptions!$C$5:$C$8,D10)-INDEX(Assumptions!$B$5:$B$8,D10))/3 -> 4 | F10: =(INDEX(Assumptions!$D$5:$D$8,$D10)+(INDEX(Assumptions!$E$5:$E$8,$D10)-INDEX(Assumptions!$D$5:$D$8,$D10))*Assumptions!$B$11)/$E10 -> 42500 | G10: =(INDEX(Assumptions!$D$5:$D$8,$D10)+(INDEX(Assumptions!$E$5:$E$8,$D10)-INDEX(Assumptions!$D$5:$D$8,$D10))*Assumptions!$B$12)/$E10 -> 55000 | H10: =(INDEX(Assumptions!$D$5:$D$8,$D10)+(INDEX(Assumptions!$E$5:$E$8,$D10)-INDEX(Assumptions!$D$5:$D$8,$D10))*Assumptions!$B$13)/$E10 -> 67500 | I10: =SUM(F$5:F10) -> 212500 | J10: =SUM(G$5:G10) -> 275000 | K10: =SUM(H$5:H10) -> 337500
A11: Q7 | B11: 18 | C11: =B11+3 -> 21 | D11: =MATCH(B11,Assumptions!$B$5:$B$8,1) -> 3 | E11: =(INDEX(Assumptions!$C$5:$C$8,D11)-INDEX(Assumptions!$B$5:$B$8,D11))/3 -> 4 | F11: =(INDEX(Assumptions!$D$5:$D$8,$D11)+(INDEX(Assumptions!$E$5:$E$8,$D11)-INDEX(Assumptions!$D$5:$D$8,$D11))*Assumptions!$B$11)/$E11 -> 136250 | G11: =(INDEX(Assumptions!$D$5:$D$8,$D11)+(INDEX(Assumptions!$E$5:$E$8,$D11)-INDEX(Assumptions!$D$5:$D$8,$D11))*Assumptions!$B$12)/$E11 -> 180000 | H11: =(INDEX(Assumptions!$D$5:$D$8,$D11)+(INDEX(Assumptions!$E$5:$E$8,$D11)-INDEX(Assumptions!$D$5:$D$8,$D11))*Assumptions!$B$13)/$E11 -> 223750 | I11: =SUM(F$5:F11) -> 348750 | J11: =SUM(G$5:G11) -> 455000 | K11: =SUM(H$5:H11) -> 561250
A12: Q8 | B12: 21 | C12: =B12+3 -> 24 | D12: =MATCH(B12,Assumptions!$B$5:$B$8,1) -> 3 | E12: =(INDEX(Assumptions!$C$5:$C$8,D12)-INDEX(Assumptions!$B$5:$B$8,D12))/3 -> 4 | F12: =(INDEX(Assumptions!$D$5:$D$8,$D12)+(INDEX(Assumptions!$E$5:$E$8,$D12)-INDEX(Assumptions!$D$5:$D$8,$D12))*Assumptions!$B$11)/$E12 -> 136250 | G12: =(INDEX(Assumptions!$D$5:$D$8,$D12)+(INDEX(Assumptions!$E$5:$E$8,$D12)-INDEX(Assumptions!$D$5:$D$8,$D12))*Assumptions!$B$12)/$E12 -> 180000 | H12: =(INDEX(Assumptions!$D$5:$D$8,$D12)+(INDEX(Assumptions!$E$5:$E$8,$D12)-INDEX(Assumptions!$D$5:$D$8,$D12))*Assumptions!$B$13)/$E12 -> 223750 | I12: =SUM(F$5:F12) -> 485000 | J12: =SUM(G$5:G12) -> 635000 | K12: =SUM(H$5:H12) -> 785000
A13: Q9 | B13: 24 | C13: =B13+3 -> 27 | D13: =MATCH(B13,Assumptions!$B$5:$B$8,1) -> 3 | E13: =(INDEX(Assumptions!$C$5:$C$8,D13)-INDEX(Assumptions!$B$5:$B$8,D13))/3 -> 4 | F13: =(INDEX(Assumptions!$D$5:$D$8,$D13)+(INDEX(Assumptions!$E$5:$E$8,$D13)-INDEX(Assumptions!$D$5:$D$8,$D13))*Assumptions!$B$11)/$E13 -> 136250 | G13: =(INDEX(Assumptions!$D$5:$D$8,$D13)+(INDEX(Assumptions!$E$5:$E$8,$D13)-INDEX(Assumptions!$D$5:$D$8,$D13))*Assumptions!$B$12)/$E13 -> 180000 | H13: =(INDEX(Assumptions!$D$5:$D$8,$D13)+(INDEX(Assumptions!$E$5:$E$8,$D13)-INDEX(Assumptions!$D$5:$D$8,$D13))*Assumptions!$B$13)/$E13 -> 223750 | I13: =SUM(F$5:F13) -> 621250 | J13: =SUM(G$5:G13) -> 815000 | K13: =SUM(H$5:H13) -> 1008750
A14: Q10 | B14: 27 | C14: =B14+3 -> 30 | D14: =MATCH(B14,Assumptions!$B$5:$B$8,1) -> 3 | E14: =(INDEX(Assumptions!$C$5:$C$8,D14)-INDEX(Assumptions!$B$5:$B$8,D14))/3 -> 4 | F14: =(INDEX(Assumptions!$D$5:$D$8,$D14)+(INDEX(Assumptions!$E$5:$E$8,$D14)-INDEX(Assumptions!$D$5:$D$8,$D14))*Assumptions!$B$11)/$E14 -> 136250 | G14: =(INDEX(Assumptions!$D$5:$D$8,$D14)+(INDEX(Assumptions!$E$5:$E$8,$D14)-INDEX(Assumptions!$D$5:$D$8,$D14))*Assumptions!$B$12)/$E14 -> 180000 | H14: =(INDEX(Assumptions!$D$5:$D$8,$D14)+(INDEX(Assumptions!$E$5:$E$8,$D14)-INDEX(Assumptions!$D$5:$D$8,$D14))*Assumptions!$B$13)/$E14 -> 223750 | I14: =SUM(F$5:F14) -> 757500 | J14: =SUM(G$5:G14) -> 995000 | K14: =SUM(H$5:H14) -> 1232500
A15: Q11 | B15: 30 | C15: =B15+3 -> 33 | D15: =MATCH(B15,Assumptions!$B$5:$B$8,1) -> 4 | E15: =(INDEX(Assumptions!$C$5:$C$8,D15)-INDEX(Assumptions!$B$5:$B$8,D15))/3 -> 6 | F15: =(INDEX(Assumptions!$D$5:$D$8,$D15)+(INDEX(Assumptions!$E$5:$E$8,$D15)-INDEX(Assumptions!$D$5:$D$8,$D15))*Assumptions!$B$11)/$E15 -> 283333.33 | G15: =(INDEX(Assumptions!$D$5:$D$8,$D15)+(INDEX(Assumptions!$E$5:$E$8,$D15)-INDEX(Assumptions!$D$5:$D$8,$D15))*Assumptions!$B$12)/$E15 -> 366666.67 | H15: =(INDEX(Assumptions!$D$5:$D$8,$D15)+(INDEX(Assumptions!$E$5:$E$8,$D15)-INDEX(Assumptions!$D$5:$D$8,$D15))*Assumptions!$B$13)/$E15 -> 450000 | I15: =SUM(F$5:F15) -> 1040833.3 | J15: =SUM(G$5:G15) -> 1361666.7 | K15: =SUM(H$5:H15) -> 1682500
A16: Q12 | B16: 33 | C16: =B16+3 -> 36 | D16: =MATCH(B16,Assumptions!$B$5:$B$8,1) -> 4 | E16: =(INDEX(Assumptions!$C$5:$C$8,D16)-INDEX(Assumptions!$B$5:$B$8,D16))/3 -> 6 | F16: =(INDEX(Assumptions!$D$5:$D$8,$D16)+(INDEX(Assumptions!$E$5:$E$8,$D16)-INDEX(Assumptions!$D$5:$D$8,$D16))*Assumptions!$B$11)/$E16 -> 283333.33 | G16: =(INDEX(Assumptions!$D$5:$D$8,$D16)+(INDEX(Assumptions!$E$5:$E$8,$D16)-INDEX(Assumptions!$D$5:$D$8,$D16))*Assumptions!$B$12)/$E16 -> 366666.67 | H16: =(INDEX(Assumptions!$D$5:$D$8,$D16)+(INDEX(Assumptions!$E$5:$E$8,$D16)-INDEX(Assumptions!$D$5:$D$8,$D16))*Assumptions!$B$13)/$E16 -> 450000 | I16: =SUM(F$5:F16) -> 1324166.7 | J16: =SUM(G$5:G16) -> 1728333.3 | K16: =SUM(H$5:H16) -> 2132500
... A20: Q16 | B20: 45 | C20: =B20+3 -> 48 | D20: =MATCH(B20,Assumptions!$B$5:$B$8,1) -> 4 | E20: =(INDEX(Assumptions!$C$5:$C$8,D20)-INDEX(Assumptions!$B$5:$B$8,D20))/3 -> 6 | F20: =(INDEX(Assumptions!$D$5:$D$8,$D20)+(INDEX(Assumptions!$E$5:$E$8,$D20)-INDEX(Assumptions!$D$5:$D$8,$D20))*Assumptions!$B$11)/$E20 -> 283333.33 | G20: =(INDEX(Assumptions!$D$5:$D$8,$D20)+(INDEX(Assumptions!$E$5:$E$8,$D20)-INDEX(Assumptions!$D$5:$D$8,$D20))*Assumptions!$B$12)/$E20 -> 366666.67 | H20: =(INDEX(Assumptions!$D$5:$D$8,$D20)+(INDEX(Assumptions!$E$5:$E$8,$D20)-INDEX(Assumptions!$D$5:$D$8,$D20))*Assumptions!$B$13)/$E20 -> 450000 | I20: =SUM(F$5:F20) -> 2457500 | J20: =SUM(G$5:G20) -> 3195000 | K20: =SUM(H$5:H20) -> 3932500
A21: Total | F21: =SUM(F5:F20) -> 2457500 | G21: =SUM(G5:G20) -> 3195000 | H21: =SUM(H5:H20) -> 3932500

Sheet Scenarios
A1: Scenarios: what you would need, and what you might have achieved
A2: Outcomes are milestones, not revenue forecasts. Funding secured is for you to fill in (yellow): it is blank because I do not know what you have raised or been promised.
A4: Scenario | B4: Need by month (A) | C4: Need by month (B) | D4: Need by month (C) | E4: Funding secured so far (US$) | F4: Gap at month (B) | G4: Outcomes at about 36 months
A5: Months checked: | B5: 18 | C5: 36 | D5: 48
A6: Conservative | B6: =SUMIFS(Roadmap_Budget!$F$5:$F$20,Roadmap_Budget!$C$5:$C$20,"<="&B$5) -> 212500 | C6: =SUMIFS(Roadmap_Budget!$F$5:$F$20,Roadmap_Budget!$C$5:$C$20,"<="&C$5) -> 1324166.7 | D6: =SUMIFS(Roadmap_Budget!$F$5:$F$20,Roadmap_Budget!$C$5:$C$20,"<="&D$5) -> 2457500 | E6: 0 | F6: =C6-E6 -> 1324166.7 | G6: Intellectual property filed and a documented data collection built. One or two academic collaborations. Funded mostly by grants.
A7: Base case | B7: =SUMIFS(Roadmap_Budget!$G$5:$G$20,Roadmap_Budget!$C$5:$C$20,"<="&B$5) -> 275000 | C7: =SUMIFS(Roadmap_Budget!$G$5:$G$20,Roadmap_Budget!$C$5:$C$20,"<="&C$5) -> 1728333.3 | D7: =SUMIFS(Roadmap_Budget!$G$5:$G$20,Roadmap_Budget!$C$5:$C$20,"<="&D$5) -> 3195000 | E7: 0 | F7: =C7-E7 -> 1728333.3 | G7: Everything in the conservative case, plus a sponsored research or collaboration agreement with an industry partner, validated early results in at least one program, and follow-on funding secured.
A8: Upside | B8: =SUMIFS(Roadmap_Budget!$H$5:$H$20,Roadmap_Budget!$C$5:$C$20,"<="&B$5) -> 337500 | C8: =SUMIFS(Roadmap_Budget!$H$5:$H$20,Roadmap_Budget!$C$5:$C$20,"<="&C$5) -> 2132500 | D8: =SUMIFS(Roadmap_Budget!$H$5:$H$20,Roadmap_Budget!$C$5:$C$20,"<="&D$5) -> 3932500 | E8: 0 | F8: =C8-E8 -> 2132500 | G8: Everything in the base case, plus an option or licence agreement with a biotech or pharma partner and a regional training and laboratory partnership.
A10: Reading this table | B10: Need by month (A, B, C) is the cumulative spend in that scenario up to those months. Gap = need at month (B) minus the funding you have secured. A negative gap means you are ahead of the plan.

Sheet Market_Context
A1: Market and need: sourced figures
A2: Third-party estimates. They disagree because they define the market differently (plasmid only vs. including viral vectors) and use different growth assumptions.
A4: Metric | B4: Source | C4: Base year | D4: Base value | E4: Target year | F4: Target value | G4: Years | H4: Implied annual growth | I4: Unit | J4: Note
A5: Plasmid DNA manufacturing (plasmid only) | B5: Grand View Research, 2025 to 2033 report | C5: 2024 | D5: 0.8 | E5: 2033 | F5: 5.04 | G5: =VALUE(E5)-VALUE(C5) -> 9 | H5: =IF(AND(D5>0,G5>0),(F5/D5)^(1/G5)-1,0) -> 0.22691822 | I5: US$ billion | J5: Report states a 23.06% CAGR from 2025.
A6: Plasmid DNA manufacturing (plasmid only) | B6: Market.us, release of February 2026 | C6: 2023 | D6: 1.1857 | E6: 2033 | F6: 8.5445 | G6: =VALUE(E6)-VALUE(C6) -> 10 | H6: =IF(AND(D6>0,G6>0),(F6/D6)^(1/G6)-1,0) -> 0.21834752 | I6: US$ billion | J6: Report states a 21.8% CAGR.
A7: Viral vector and plasmid DNA manufacturing | B7: Astute Analytica, release of 25 August 2025 | C7: 2024 | D7: 4.21 | E7: 2033 | F7: 20.3 | G7: =VALUE(E7)-VALUE(C7) -> 9 | H7: =IF(AND(D7>0,G7>0),(F7/D7)^(1/G7)-1,0) -> 0.19100246 | I7: US$ billion | J7: Report states a 19.1% CAGR.
A8: Viral vector and plasmid DNA manufacturing | B8: Allied Market Research, release of 2026 | C8: 2023 | D8: 5.3 | E8: 2033 | F8: 34 | G8: =VALUE(E8)-VALUE(C8) -> 10 | H8: =IF(AND(D8>0,G8>0),(F8/D8)^(1/G8)-1,0) -> 0.20426012 | I8: US$ billion | J8: Report states a 20.4% CAGR.
A9: Deaths directly caused by bacterial antimicrobial resistance, per year | B9: GBD 2021 Antimicrobial Resistance Collaborators, The Lancet, 16 Sept 2024 | C9: 2021 | D9: 1.14 | E9: 2050 | F9: 1.91 | G9: =VALUE(E9)-VALUE(C9) -> 29 | H9: =IF(AND(D9>0,G9>0),(F9/D9)^(1/G9)-1,0) -> 0.017954976 | I9: million deaths per year | J9: Cumulative 2025 to 2050: more than 39 million (reference scenario 39.1 million). New Gram-negative antibiotics could avert about 11 million.
A11: Range of 2033 estimates, plasmid only (US$ billion) | B11: =MIN(F5:F6) -> 5.04 | C11: to | D11: =MAX(F5:F6) -> 8.5445
A12: Range of 2033 estimates, combined with viral vectors (US$ billion) | B12: =MIN(F7:F8) -> 20.3 | C12: to | D12: =MAX(F7:F8) -> 34 | J12: Other reports go as high as about 39. This is why the website shows ranges.
A14: Coastal pressure (context for ThermoDen) | B14: Source | C14: Year | D14: Value | I14: Unit | J14: Note
A15: Sargassum recorded in the Atlantic, record total | B15: UNEP Caribbean Environment Programme | C15: 2025 | D15: 37.5 | I15: million metric tonnes | J15: May 2025; highest since monitoring began in 2011.
A16: Estimated cost of cleaning up excess sargassum across the Caribbean | B16: US Environmental Protection Agency | C16: 2018 | D16: 120 | I16: US$ million | J16: EPA fact sheet on sargassum inundation events.
A17: Sargassum projected to reach Quintana Roo, Mexico | B17: Reuters, 28 July 2026 | C17: 2026 | D17: 119000 | I17: tonnes | J17: Previous record 96,000 tonnes. State governor puts management costs at about 11% of state GDP.

Sheet Corrections_Log
A1: Corrections log: inconsistencies found in your documents and website, and what I changed
A3: # | B3: Where | C3: What it said | D3: The problem | E3: What I did | F3: Evidence
A4: 1 | B4: Old website: footer and IP page | C4: "Patent Pending" and "Patent applications in progress" | D4: Your own IP guide shows no application filed yet (attorney, prior-art search and provisional are still ahead). Saying "patent pending" without a pending application can mislead and can be treated as false marking (35 U.S.C. 292). | E4: Removed. New sites say the IP strategy is "in development". A switch (PATENT_FILED) turns the wording on once you really have filed. | F4: Patent Opportunities guide, step list and tentative schedule. Ask counsel.
A5: 2 | B5: Old website: home page stats | C5: "~0 prior systematic studies of Caribbean hot spring microbiomes" | D5: Your own proposals cite a published foundational survey of these springs, so "zero" is not accurate. | E5: Now: "few published surveys; commercial development largely unexplored". | F5: Hot Springs 1 and 2 (cite a 2009 survey).
A6: 3 | B6: Old website: home page stats | C6: "1st to access this biological territory commercially" | D6: Cannot be verified, and "first" claims invite challenge. | E6: Removed. Replaced with neutral language. | F6: None available.
A7: 4 | B7: Hot Springs 1 and old website | C7: "$14B plasmid DNA market by 2033" | D7: Published estimates range from about $5B to $8.5B for plasmid only, and about $15B to $39B when viral vectors are included. One number hides a wide, definition-driven range. | E7: Shown as ranges with the definition and four named sources (see Market_Context). | F7: Grand View Research; Market.us; Astute Analytica; Allied Market Research.
A8: 5 | B8: Old website: Technology and Home | C8: "We have developed a proprietary platform"; "we screen novel isolates against WHO priority pathogens" | D8: Your proposals describe a concept stage: the pilot study has not been run yet ("our next step"). | E8: Reworded to "concept and planning stage; pilot planned". Investors and partners will check, so claims must match the stage. | F8: Hot Springs 1, "Our next step".
A9: 6 | B9: Hot Springs 1 and old website | C9: Sell a catalogue of natural plasmids for gene therapy and vaccines | D9: Therapeutic plasmids are made to defined, manufacturing-grade standards in standard production hosts, and your own notes flag characterisation, stability and regulatory hurdles. Raw natural plasmids are unlikely to be a direct product. | E9: Reframed around what is realistic: curated data and strains, new genetic parts and enzymes, and licensing or collaboration. | F9: Hot Springs 1 ("Some major challenges"); market reports focus on GMP-grade.
A10: 7 | B10: Patent Opportunities guide | C10: Provisional filing fee "roughly $350 for small entities" | D10: USPTO fees are $65 (micro), $130 (small) and $325 (large) since January 2025. | E10: Corrected in the model, with an entity-status switch. | F10: 37 CFR 1.16(d); USPTO fee schedule.
A11: 8 | B11: Patent Opportunities guide | C11: Budget "$350 to $1,000" at the provisional stage | D11: That only works if you prepare the provisional yourself. A professionally prepared biotech provisional commonly costs a few thousand dollars in attorney time on top of the filing fee. | E11: Both shown: government fee plus an attorney range of $4,000 to $5,000 (one 2026 pricing guide). Get quotes. | F11: IP Boutique Law, 2026 provisional cost guide.
A12: 9 | B12: Patent Opportunities guide | C12: "Publish to establish priority" and "do not disclose before filing" | D12: These conflict unless sequenced: in many countries public disclosure before filing ends patent rights. | E12: Sequence set as: file the provisional first, then present or publish. Written on the IP_Pipeline sheet. | F12: Your guide, step 4.
A13: 10 | B13: Hot Springs 2 | C13: Clean-up costs of "US$1 million per kilometre" and France's "EUR 53.9 million" | D13: I could not verify these figures. | E13: Replaced on the public site with sourced figures (EPA, UNEP, Reuters). Please verify the originals before reusing them. | F13: See Market_Context.
A14: 11 | B14: Hot Springs 2 and 5 | C14: References dated 2025 and 2026; a "Hotsprings 3" document | D14: I could not check these, and Hotsprings 3 was not provided. | E14: Not used on the public sites. Verify every citation before it goes into a grant or patent. | F14: n/a
A15: 12 | B15: Lab Experiments document | C15: Experiment 1 measures copper and zinc "with the Hach kit" | D15: The materials list includes only an arsenic kit, so copper and zinc could not be measured as written. | E15: Added as an unfunded line on Assumptions. | F15: Lab Experiments document, materials table vs. Experiment 1.
... A20: 17 | B20: Your resume vs. the website | C20: Founder bio | D20: Consistent, but your resume includes private details and a ministry role. | E20: Public bio uses degrees, roles, honours, publications and languages. Phone, home address and personal email left off. MDiv included in education; the pastoral role is left out (you can add it). | F20: Resume provided.
